bosing/__init__.py
bosing/_bosing.cpython-313t-darwin.so
bosing/_bosing.pyi
bosing/_plot.py
bosing/py.typed
bosing-2.7.0.dist-info/METADATA
bosing-2.7.0.dist-info/WHEEL
bosing-2.7.0.dist-info/licenses/LICENSE.txt
bosing-2.7.0.dist-info/RECORD
