Metadata-Version: 2.4
Name: bosing
Version: 2.7.0
Classifier: Development Status :: 3 - Alpha
Classifier: Programming Language :: Rust
Classifier: Programming Language :: Python :: Implementation :: CPython
Classifier: Programming Language :: Python :: Implementation :: PyPy
Classifier: Intended Audience :: Science/Research
Classifier: Topic :: Scientific/Engineering
Classifier: License :: OSI Approved :: MIT License
Requires-Dist: matplotlib>=3.5.0
Requires-Dist: numpy>=1.19.3
License-File: LICENSE.txt
Summary: Waveform generator for pulse sequences in quantum computing
Keywords: pulse,waveform,awg
Author: Jiahao Yuan <kahojyun@icloud.com>
Author-email: Jiahao Yuan <kahojyun@icloud.com>
License: MIT
Requires-Python: >=3.10
Project-URL: Documentation, https://bosing.readthedocs.io
Project-URL: Issues, https://github.com/kahojyun/Bosing/issues
Project-URL: Source, https://github.com/kahojyun/Bosing
